{
  "id": "hermes-bolide",
  "order": 100,
  "cat": "bags",
  "brand": "Hermes",
  "collection": "Bolide",
  "type": "Сумки",
  "model": "Bolide",
  "price": 330000,
  "condition": "Отличное",
  "conditionNote": "Состояние - отличное. Есть незначительные следы аккуратной носки",
  "status": "available",
  "specs": {
    "color": "Зеленый",
    "size": "31,5 × 23,5 × 12,5 см",
    "complect": "Только сумка"
  },
  "auth": "expert",
  "photos": [
    "/photos/Hermes-1.png",
    "/photos/Hermes1.png",
    "/photos/Hermes2.png",
    "/photos/Hermes3.png"
  ],
  "desc": "Bolide - сумка, которую Hermès придумал раньше, чем Birkin и Kelly. В 1923 году Эмиль-Морис Эрмес привёз из Америки новинку - застёжку-молнию - и первым в мире поставил её на дамскую сумку. До этого сумки не застёгивались наглухо; Bolide стала первой, которую можно было закрыть полностью. Отсюда куполообразный силуэт, который дом не менял сто лет.\nBolide 31 - самый носибельный размер линии: две ручки для города, съёмный ремень для плеча и кроссбоди, молния вместо клапана - быстрый доступ, которого нет у Birkin и Kelly.\n\nЦвет - Bambou: сочный травянисто-зелёный, один из тех hermèsовских оттенков, ради которых охотятся за конкретным годом. Не базовый чёрный, который есть у всех, - цвет, который запоминается. Кожа Clemence (Taurillon Clemence) — мягкая, зернистая, с лёгким естественным блеском, приятно тяжёлая в руке. Фурнитура - палладий.\n\nРазмеры: 31,5 × 23,5 × 12,5 см, съёмный ремень 90 см. Год - 2014 (штамп R в квадрате)."
}