{
  "id": "lv-keepall-bandouliere-white-monogram",
  "order": 34,
  "cat": "bags",
  "brand": "Louis Vuitton",
  "collection": "Keepall",
  "type": "Дорожные сумки",
  "model": "Keepall America's Cup 50",
  "price": 280000,
  "condition": "Отличное",
  "conditionNote": "В отличном состоянии, фактически без следов носки.",
  "status": "available",
  "specs": {
    "color": "Белый монограм",
    "complect": "Только сумка"
  },
  "auth": "entrupy",
  "photos": [
    "/photos/LV_Keepall_Bandouliere_White_Monogram_01.jpg",
    "/photos/LV_Keepall_Bandouliere_White_Monogram_03.jpg",
    "/photos/LV_Keepall_Bandouliere_White_Monogram_02.jpg"
  ],
  "desc": "Louis Vuitton Keepall. За 90 лет существования модель стала холстом для большинства громких релизов LV. Лимитированные коллекции снимаются с производства за один-два сезона, после чего найти их можно только на ресейле - и цены там растут год от года.\n\nAmerica's Cup 50 — специальный выпуск к 37-му Кубку Америки, нишевая коллекционная позиция."
}